MANIFEST.in
README.rst
VERSION
setup.cfg
setup.py
py_disk_imager.egg-info/PKG-INFO
py_disk_imager.egg-info/SOURCES.txt
py_disk_imager.egg-info/dependency_links.txt
py_disk_imager.egg-info/top_level.txt
pysfdisk/__init__.py
pysfdisk/block_device.py
pysfdisk/errors.py
pysfdisk/partition.py
pysfdisk/example/example.py