Metadata-Version: 2.1
Name: py-disk-imager
Version: 1.0.1
Summary: UNKNOWN
Home-page: https://github.com/beskidinstruments/python-sfdisk
Author: Matt Comben, Tomasz Szuster
Author-email: matthew@dockstudios.co.uk, tomasz.szuster@gmail.com
License: GNU GENERAL PUBLIC LICENSE
Platform: UNKNOWN
Classifier: Programming Language :: Python :: 3.6
Classifier: Programming Language :: Python :: 3.7
Classifier: Programming Language :: Python :: 3.8
Classifier: License :: OSI Approved :: MIT License
Classifier: Operating System :: POSIX :: Linux
